.gitignore
LICENSE
MANIFEST.in
README.rst
requirements.txt
setup.py
dashboardmods/__init__.py
dashboardmods/admin.py
dashboardmods/models.py
dashboardmods/modules.py
dashboardmods.egg-info/PKG-INFO
dashboardmods.egg-info/SOURCES.txt
dashboardmods.egg-info/dependency_links.txt
dashboardmods.egg-info/top_level.txt
dashboardmods/templates/dashboard/modules/memcache.html
doc_src/Makefile
doc_src/conf.py
doc_src/getting_started.rst
doc_src/index.rst
doc_src/installation.rst
doc_src/make.bat
doc_src/_static/breadcrumb_background.png
doc_src/_static/default.css
doc_src/_static/documentation.png
doc_src/_static/header_sm_mid.png
doc_src/_static/scrn1.png
doc_src/_static/scrn2.png
doc_src/_static/searchfield_leftcap.png
doc_src/_static/searchfield_repeat.png
doc_src/_static/searchfield_rightcap.png
doc_src/_static/title_background.png
doc_src/_static/toc.js
doc_src/_static/triangle_closed.png
doc_src/_static/triangle_left.png
doc_src/_static/triangle_open.png
doc_src/_templates/layout.html
doc_src/reference/index.rst
doc_src/reference/settings.rst